iplkp/__init__.py
iplkp/cache.py
iplkp/consts.py
iplkp/utils.py
iplkp/lookup/__init__.py
iplkp/lookup/geo_ip.py
iplkp/lookup/rdap.py
out_of_scope/__init__.py
out_of_scope/ar.py
out_of_scope/sleep_test.py
tests/__init__.py
tests/test_cache.py
tests/lookup/__init__.py
tests/lookup/test_geo_ip.py
tests/lookup/test_rdap.py
iplkp-1.0.0.dist-info/LICENSE
iplkp-1.0.0.dist-info/METADATA
iplkp-1.0.0.dist-info/WHEEL
iplkp-1.0.0.dist-info/entry_points.txt
iplkp-1.0.0.dist-info/top_level.txt
iplkp-1.0.0.dist-info/RECORD
